wsbridge/#todo.py
wsbridge/__init__.py
wsbridge/baseclient.py
wsbridge/simpleservice.py
wsbridge-0.5.dist-info/LICENSE
wsbridge-0.5.dist-info/METADATA
wsbridge-0.5.dist-info/WHEEL
wsbridge-0.5.dist-info/top_level.txt
wsbridge-0.5.dist-info/RECORD
