Metadata-Version: 2.1
Name: wsbridge
Version: 0.5
Summary: # todo
Author-email: "Adrian F. Hoefflin" <srccircumflex@outlook.com>
License: MIT License
Project-URL: Repository, https://github.com/srccircumflex/wsbridge
Keywords: ws,websocket,proxy
Classifier: Topic :: Communications
Classifier: Programming Language :: Python :: 3.10
Classifier: Programming Language :: Python :: 3.11
Classifier: Programming Language :: Python :: 3.12
Classifier: Programming Language :: Python :: 3.13
Classifier: Programming Language :: Python :: 3.14
Requires-Python: >=3.10
License-File: LICENSE
Requires-Dist: wsdatautil>=1.1
